setup.py
gaetasks/__init__.py
gaetasks/handler.py
gaetasks/task.py
gaetasks.egg-info/PKG-INFO
gaetasks.egg-info/SOURCES.txt
gaetasks.egg-info/dependency_links.txt
gaetasks.egg-info/not-zip-safe
gaetasks.egg-info/top_level.txt