Metadata-Version: 1.1
Name: gaetasks
Version: 0.0.2
Summary: Better google appengine deferred lib
Home-page: UNKNOWN
Author: Konrad Rotkiewicz
Author-email: konrad.rotkiewicz@gmail.com
License: UNKNOWN
Keywords: appengine gae defer deferred
Platform: UNKNOWN
Classifier: Programming Language :: Python
Classifier: Programming Language :: Python :: 2.7
